LICENSE.md
MANIFEST.in
README.rst
setup.py
intersectshape/__init__.py
intersectshape/intersectshape.py
intersectshape/spatialindex.py
intersectshape.egg-info/PKG-INFO
intersectshape.egg-info/SOURCES.txt
intersectshape.egg-info/dependency_links.txt
intersectshape.egg-info/requires.txt
intersectshape.egg-info/top_level.txt