Metadata-Version: 1.0
Name: intersectshape
Version: 0.1.1
Summary: Reverse geocoding from a shapefile of polygons.
Home-page: https://github.com/jnth/intersectshape
Author: Jonathan Virga
Author-email: jonathan.virga@gmail.com
License: GNU GPL v3
Platform: UNKNOWN
